{
    "industry": [
        {
            "type": "electronic",
            "name": "電子業",
            "url": "/tw/dsc/solution/WB002513/WB00251301.html",
            "solution": [
                {
                    "require": "1.管控廠內生產排程、交期及品質",
                    "description": "直通率報表，監控生產線品質水準，物料供應異常，安裝電子看板、物料看板即時追蹤",
                    "illust": {
                        "A1-1": "排程缺料警訊看板",
                        "A1-2": "製令領料警訊看板"
                    }
                },
                {
                    "require": "2.組裝生產線組裝需要大量人力作業",
                    "description": "多人報工，即時從機台取得生產數量及工時",
                    "illust": {
                        "A2-1": "條碼報工",
                        "A2-2": "製令輸入",
                        "A2-3": "設備稼動率分析表",
                        "A2-4": "KMI報工"
                    }
                },
                {
                    "require": "3.訂單出貨後的產品追溯",
                    "description": "透過eKB看版，將有問題的產品序號追蹤可視化，有效回溯管理生產流程",
                    "illust": {
                        "A3-1": "eKB看版-生產回溯報表"
                    }
                }
            ]
        },
        {
            "type": "mechanical",
            "name": "機械業",
            "url": "/tw/dsc/solution/WB002476/WB00247601.html",
            "solution": [
                {
                    "require": "1.管控廠內生產排程、交期及品質",
                    "description": "即時整合BOM結構，依物料需求區分，快速擬定訂單用料",
                    "illust": {
                        "B1-1": "物料在途看板",
                        "B1-2": "採購追料警訊看板"
                    }
                },
                {
                    "require": "2.多道工序同時加工，現場料況追蹤",
                    "description": "不良品質管理功能，不良原因分析，更清楚生產狀況，降低不良品衍生的成本",
                    "illust": {
                        "B2-1": "生產線良率看板",
                        "B2-2": "不良品原因明細表",
                        "B2-3": "不良原因分析"
                    }
                },
                {
                    "require": "3.訂單多樣少量，需要頻繁更換生產線",
                    "description": "現場製令/機台/派工查詢，快速安排加工順序，混線生產，彈性製造",
                    "illust": {
                        "B3-1": "派工看板",
                        "B3-2": "預計加工看板"
                    }
                },
                {
                    "require": "4.需要立即了解物料與機台閒置狀況",
                    "description": "透過eKB電子看板，將閒置或逾期製令看板可視化，查詢哪道工序閒置或延遲過久",
                    "illust": {
                        "B4-1": "閒置製令看板",
                        "B4-2": "電子看板-閒置製令看板"
                    }
                }
            ]
        },
        {
            "type": "plastic",
            "name": "塑膠業",
            "url": "/tw/dsc/solution/WB002554/WB00255401.html",
            "solution": [
                {
                    "require": "<strong>1.生產線產能利用率不佳</strong><br>不確定製程是塞車還是閒置狀態",
                    "description": "生產現場機台查詢，指定機台派工，系統化排程分配",
                    "illust": {
                        "C1-1": "線上派工",
                        "C1-2": "閒置製令看板"
                    }
                },
                {
                    "require": "<strong>2.生產進度無法掌握，盲！</strong><br>時常逾期、短少、超交情況",
                    "description": "即時查詢廠內生產進度，進而預測訂單、承諾交期快速回應訂單進度",
                    "illust": {
                        "C2-1": "生產看板",
                        "C2-2": "製程生產狀況看板"
                    }
                },
                {
                    "require": "<strong>3.一穴多模的共模管理，雜！</strong><br>此行業需重視一模多穴-共模的模具管理，若以人工記錄資料未能即時更新",
                    "description": "利用制令工單中，可選出目前可用的模仁輕鬆做到共模管理",
                    "illust": {
                        "C3-1": "進站",
                        "C3-2": "報工",
                        "C3-3": "進站-根據上架的模具列出目前可用的模仁",
                        "C3-4": "進站-可輸入多筆原料及使用數量"
                    }
                }
            ]
        },
        {
            "type": "metal",
            "name": "交通業",
            "url": "/tw/dsc/solution/WB002811/WB00281101.html",
            "solution": [
                {
                    "require": "1.總是要打電話才能追蹤外包廠商的生產進度與品質，有時候還找不到人問？",
                    "description": "隨手便利，操作簡易，減少人力、資料即時，即時監控掌握廠商生產現況",
                    "illust": {
                        "E1-1": "外包管理流程",
                        "E1-2": "手機e報工"
                    }
                },
                {
                    "require": "2.人工手動抄寫數量、工時…等，生產數據收集後，再登打到excel做履歷或分析，助理有時會記錄錯誤？",
                    "description": "現場即時報工回饋，落實生產紀錄",
                    "illust": {
                        "E2-1": "派工看板管理"
                    }
                },
                {
                    "require": "3.生產時找不到模具，因為上次用完未歸位，要上線才發現模具有問題，導致等待及時間浪費。",
                    "description": "設定模具歸還狀態，生產不延遲",
                    "illust": {
                        "E3-1": "模具歸還"
                    }
                }
            ]
        }
    ]
}